LICENSE
MANIFEST.in
README
setup.py
pyghelpers/__init__.py
pyghelpers/conf.py
pyghelpers/pyghelpers.py
pyghelpers.egg-info/PKG-INFO
pyghelpers.egg-info/SOURCES.txt
pyghelpers.egg-info/dependency_links.txt
pyghelpers.egg-info/requires.txt
pyghelpers.egg-info/top_level.txt
pyghelpers_test/__init__.py
pyghelpers_test/DialogTester/Main_DialogTester.py
pyghelpers_test/DialogTester/__init__.py
pyghelpers_test/DialogTester/images/addDisabled.png
pyghelpers_test/DialogTester/images/addDown.png
pyghelpers_test/DialogTester/images/addNormal.png
pyghelpers_test/DialogTester/images/addOver.png
pyghelpers_test/DialogTester/images/cancelDisabled.png
pyghelpers_test/DialogTester/images/cancelDown.png
pyghelpers_test/DialogTester/images/cancelNormal.png
pyghelpers_test/DialogTester/images/cancelOver.png
pyghelpers_test/DialogTester/images/controlsBackground.jpg
pyghelpers_test/DialogTester/images/dialog.png
pyghelpers_test/DialogTester/images/highScoresBackground.jpg
pyghelpers_test/DialogTester/images/noDisabled.png
pyghelpers_test/DialogTester/images/noDown.png
pyghelpers_test/DialogTester/images/noNormal.png
pyghelpers_test/DialogTester/images/noOver.png
pyghelpers_test/DialogTester/images/noThanksDisabled.png
pyghelpers_test/DialogTester/images/noThanksDown.png
pyghelpers_test/DialogTester/images/noThanksNormal.png
pyghelpers_test/DialogTester/images/noThanksOver.png
pyghelpers_test/DialogTester/images/okDisabled.png
pyghelpers_test/DialogTester/images/okDown.png
pyghelpers_test/DialogTester/images/okNormal.png
pyghelpers_test/DialogTester/images/okOver.png
pyghelpers_test/DialogTester/images/yesDisabled.png
pyghelpers_test/DialogTester/images/yesDown.png
pyghelpers_test/DialogTester/images/yesNormal.png
pyghelpers_test/DialogTester/images/yesOver.png
pyghelpers_test/Dodger/Baddies.py
pyghelpers_test/Dodger/Constants.py
pyghelpers_test/Dodger/Goodies.py
pyghelpers_test/Dodger/HighScoresData.py
pyghelpers_test/Dodger/Main_Dodger.py
pyghelpers_test/Dodger/Player.py
pyghelpers_test/Dodger/SceneExample.py
pyghelpers_test/Dodger/SceneHighScores.py
pyghelpers_test/Dodger/ScenePlay.py
pyghelpers_test/Dodger/SceneSplash.py
