Metadata-Version: 2.1
Name: pyghelpers
Version: 1.0.42
Summary: Classes and functions for use with Pygame
Home-page: https://github.com/IrvKalb/pyghelpers
Author: Irv Kalb
Author-email: Irv@furrypants.com
License: BSD
Keywords: Timer classes,Scene and SceneMgr classes,Dialogs
Classifier: Programming Language :: Python :: 3
Classifier: License :: OSI Approved :: BSD License
Classifier: Operating System :: OS Independent
License-File: LICENSE
